MANIFEST.in
README.txt
plonetheme.keepitsimple-configure.zcml
setup.py
docs/HISTORY.txt
docs/INSTALL.txt
docs/LICENSE.GPL
docs/LICENSE.txt
plonetheme/__init__.py
plonetheme.keepitsimple.egg-info/PKG-INFO
plonetheme.keepitsimple.egg-info/SOURCES.txt
plonetheme.keepitsimple.egg-info/dependency_links.txt
plonetheme.keepitsimple.egg-info/entry_points.txt
plonetheme.keepitsimple.egg-info/namespace_packages.txt
plonetheme.keepitsimple.egg-info/not-zip-safe
plonetheme.keepitsimple.egg-info/requires.txt
plonetheme.keepitsimple.egg-info/top_level.txt
plonetheme/keepitsimple/__init__.py
plonetheme/keepitsimple/configure.zcml
plonetheme/keepitsimple/profiles.zcml
plonetheme/keepitsimple/setuphandlers.py
plonetheme/keepitsimple/skins.zcml
plonetheme/keepitsimple/version.txt
plonetheme/keepitsimple/Extensions/Install.py
plonetheme/keepitsimple/Extensions/__init__.py
plonetheme/keepitsimple/browser/__init__.py
plonetheme/keepitsimple/browser/configure.zcml
plonetheme/keepitsimple/browser/interfaces.py
plonetheme/keepitsimple/browser/viewlet.pt
plonetheme/keepitsimple/browser/viewlets.py
plonetheme/keepitsimple/browser/images/README.txt
plonetheme/keepitsimple/browser/stylesheets/README.txt
plonetheme/keepitsimple/browser/templates/colophon.pt
plonetheme/keepitsimple/browser/templates/intro.pt
plonetheme/keepitsimple/browser/templates/intro_text.pt
plonetheme/keepitsimple/browser/templates/personal_bar.pt
plonetheme/keepitsimple/browser/templates/searchbox.pt
plonetheme/keepitsimple/profiles/default/browserlayer.xml
plonetheme/keepitsimple/profiles/default/cssregistry.xml
plonetheme/keepitsimple/profiles/default/import_steps.xml
plonetheme/keepitsimple/profiles/default/jsregistry.xml
plonetheme/keepitsimple/profiles/default/metadata.xml
plonetheme/keepitsimple/profiles/default/plonetheme.keepitsimple_various.txt
plonetheme/keepitsimple/profiles/default/skins.xml
plonetheme/keepitsimple/profiles/default/viewlets.xml
plonetheme/keepitsimple/profiles/uninstall/cssregistry.xml
plonetheme/keepitsimple/profiles/uninstall/skins.xml
plonetheme/keepitsimple/profiles/uninstall/viewlets.xml
plonetheme/keepitsimple/skins/plonetheme_keepitsimple_custom_images/CONTENT.txt
plonetheme/keepitsimple/skins/plonetheme_keepitsimple_custom_images/arrow-current.gif
plonetheme/keepitsimple/skins/plonetheme_keepitsimple_custom_images/arrow-inpath.gif
