Metadata-Version: 1.0
Name: plonetheme.keepitsimple
Version: 1.1a3
Summary: An installable theme for Plone 4, fluid 3-column theme, minimalistic and light colored design
Home-page: http://svn.plone.org/svn/collective/
Author: Quimera
Author-email: shuens@menttes.com
License: GPL
Keywords: web zope plone theme simple menttes
Platform: UNKNOWN
Classifier: Framework :: Plone
Classifier: Programming Language :: Python
Classifier: Topic :: Software Development :: Libraries :: Python Modules
